{
  "frames": 6,
  "assets": {
    "fastlane/metadata/android/en-US/images/phoneScreenshots/01_approve.png": {
      "width": 1080,
      "height": 1920
    },
    "fastlane/metadata/android/en-US/images/phoneScreenshots/02_block.png": {
      "width": 1080,
      "height": 1920
    },
    "fastlane/metadata/android/en-US/images/phoneScreenshots/03_standing.png": {
      "width": 1080,
      "height": 1920
    },
    "fastlane/metadata/android/en-US/images/phoneScreenshots/04_pair.png": {
      "width": 1080,
      "height": 1920
    },
    "fastlane/metadata/android/en-US/images/phoneScreenshots/05_thumbgate.png": {
      "width": 1080,
      "height": 1920
    },
    "fastlane/metadata/android/en-US/images/phoneScreenshots/06_works.png": {
      "width": 1080,
      "height": 1920
    },
    "fastlane/screenshots/en-US/01_approve_67.png": {
      "width": 1290,
      "height": 2796
    },
    "fastlane/screenshots/en-US/01_approve_ipad129.png": {
      "width": 2048,
      "height": 2732
    },
    "fastlane/screenshots/en-US/02_block_67.png": {
      "width": 1290,
      "height": 2796
    },
    "fastlane/screenshots/en-US/02_block_ipad129.png": {
      "width": 2048,
      "height": 2732
    },
    "fastlane/screenshots/en-US/03_standing_67.png": {
      "width": 1290,
      "height": 2796
    },
    "fastlane/screenshots/en-US/03_standing_ipad129.png": {
      "width": 2048,
      "height": 2732
    },
    "fastlane/screenshots/en-US/04_pair_67.png": {
      "width": 1290,
      "height": 2796
    },
    "fastlane/screenshots/en-US/04_pair_ipad129.png": {
      "width": 2048,
      "height": 2732
    },
    "fastlane/screenshots/en-US/05_thumbgate_67.png": {
      "width": 1290,
      "height": 2796
    },
    "fastlane/screenshots/en-US/05_thumbgate_ipad129.png": {
      "width": 2048,
      "height": 2732
    },
    "fastlane/screenshots/en-US/06_works_67.png": {
      "width": 1290,
      "height": 2796
    },
    "fastlane/screenshots/en-US/06_works_ipad129.png": {
      "width": 2048,
      "height": 2732
    }
  },
  "rawSimilarity": {
    "01_approve_vs_02_block": 18.31,
    "01_approve_vs_03_standing": 12.98,
    "01_approve_vs_04_pair": 12.15,
    "01_approve_vs_05_thumbgate": 17.8,
    "01_approve_vs_06_works": 20.72,
    "02_block_vs_03_standing": 26.53,
    "02_block_vs_04_pair": 22.61,
    "02_block_vs_05_thumbgate": 38.3,
    "02_block_vs_06_works": 22.7,
    "03_standing_vs_04_pair": 12.51,
    "03_standing_vs_05_thumbgate": 31.53,
    "03_standing_vs_06_works": 28.06,
    "04_pair_vs_05_thumbgate": 16.14,
    "04_pair_vs_06_works": 12.13,
    "05_thumbgate_vs_06_works": 33.08
  },
  "framedSimilarity": {
    "01_approve_vs_02_block": 43.11,
    "01_approve_vs_03_standing": 43.13,
    "01_approve_vs_04_pair": 41.16,
    "01_approve_vs_05_thumbgate": 43.7,
    "01_approve_vs_06_works": 43.95,
    "02_block_vs_03_standing": 46.15,
    "02_block_vs_04_pair": 44.91,
    "02_block_vs_05_thumbgate": 52.62,
    "02_block_vs_06_works": 48.51,
    "03_standing_vs_04_pair": 41.79,
    "03_standing_vs_05_thumbgate": 50.75,
    "03_standing_vs_06_works": 45.8,
    "04_pair_vs_05_thumbgate": 42.52,
    "04_pair_vs_06_works": 39.09,
    "05_thumbgate_vs_06_works": 49.88
  },
  "ascNote": "Only _67 + ipad129 emitted to avoid APP_IPHONE_67 double-upload"
}
